setup.py
src/__init__.py
src/s_database.py
src/s_models.py
src/s_parsers.py
src/s_periodic.py
src/s_scrape.py
src/s_scraper.py
subreddit_scraper.egg-info/PKG-INFO
subreddit_scraper.egg-info/SOURCES.txt
subreddit_scraper.egg-info/dependency_links.txt
subreddit_scraper.egg-info/requires.txt
subreddit_scraper.egg-info/top_level.txt